minkowski.libs/libgomp-a34b3233.so.1.0.0
minkowski.libs/libntl-424d9dea.so.44.0.1
minkowski.libs/libgmp-afec2dd4.so.10.2.0
minkowski-0.0.1.dist-info/RECORD
minkowski-0.0.1.dist-info/METADATA
minkowski-0.0.1.dist-info/WHEEL
minkowski-0.0.1.dist-info/licenses/LICENSE.txt
minkowski/__init__.py
minkowski/_minkowski.cpython-310-x86_64-linux-gnu.so
