Metadata-Version: 2.1
Name: minkowski
Version: 0.0.1
Summary: Fast enumeration of lattice packings in high-dimensional space.
Author-Email: Aaron Tian <atian [at] umass.edu>
License: MIT
Classifier: License :: OSI Approved :: MIT License
Project-URL: Repository, https://github.com/waiwasabi/minkowski
Requires-Python: >=3.8
